rtl/mips_register_file.v
`timescale 1ns/100ps
module mips_register_file(
    // control ports
    input logic clk,
    input logic reset,
    input logic write_enable,
    // dual input read ports & write input ports
    input logic[4:0] read_reg_1, 
    input logic[4:0] read_reg_2,
    input logic[4:0] write_reg,
    input logic[31:0] write_data,
    // dual read output ports & v0 port
    output logic[31:0] read_data_1,
    output logic[31:0] read_data_2,
    output logic[31:0] read_data_v0

);
    // create 32x32-bit register
    logic[31:0] register[31:0];

    // reset & write
    always_ff @(posedge clk) begin
        // reset register
        if(reset) begin
            for(int i = 0; i < 32; i ++)
                register[i] <= 0;
        end
        // write to register
        else begin
            if(write_enable) begin
                register[write_reg] <= write_data;
                $display("[WRITE EVENT]\tREG%d\t<-%d", write_reg, write_data);
            end
        end
    end

    // return data
    assign read_data_v0 = register[2];
    assign read_data_1 = (read_reg_1 == 0) ? 32'b0 : register[read_reg_1];
    assign read_data_2 = (read_reg_2 == 0) ? 32'b0 : register[read_reg_2];
    
endmodule

rtl/register/mips_register_file_tb.v
`timescale 1ns/100ps
module mips_register_file_tb(
);
    reg [31:0] write_data;
    reg [4:0] read_reg_1;
    reg [4:0] read_reg_2;
    reg [4:0] write_reg;
    wire [31:0] read_data_1;
    wire [31:0] read_data_2;
    wire [31:0] read_data_v0;
    reg clk;
    reg reset;
    reg write_enable;

    mips_register_file inst_reg(
        .write_data(write_data),
        .read_reg_1(read_reg_1),
        .read_reg_2(read_reg_2),
        .write_reg(write_reg),
        .read_data_1(read_data_1),
        .read_data_2(read_data_2),
        .read_data_v0(read_data_v0),
        .clk(clk),
        .reset(reset),
        .write_enable(write_enable)
    );
    
    initial begin
        $timeformat(-9, 1, " ns", 100);
        $dumpfile("mips_register_file_tb.vcd");
        $dumpvars(0, mips_register_file_tb);

        // initialise
        clk = 0;

        reset = 1;
        write_reg=0;
        write_enable=0;
        write_data=0;

        #5 clk = 1;
        #5 clk = 0;
        
        // test writing and reading single register
        $display("\n-=-=-=- TEST SINGLE WRITE & READ -=-=-=-");
        reset = 0;
        write_enable = 1;
        write_data = 1234567;
        write_reg = 16;
        read_reg_1 = 16;
        
        #5 clk = 1;
        #5 clk = 0;

        write_enable = 0;
        assert(read_data_1 == 1234567);
        $display("[READ EVENT]\tREG%d\t->%d",read_reg_1, read_data_1);

        #5 clk = 1;
        #5 clk = 0;

        // testing dual read port
        $display("\n-=-=-=- TEST DUAL READ PORTS -=-=-=-");
        write_enable = 1;
        write_data = 7654321;
        write_reg = 20;

        // dual read ports set
        read_reg_1 = 16;
        read_reg_2 = 20;

        #5 clk = 1;
        #5 clk = 0;

        write_enable = 0;
        assert(read_data_2 == 7654321);
        $display("[READ EVENT]\tREG%d\t->%d",read_reg_1, read_data_1);
        $display("[READ EVENT]\tREG%d\t->%d",read_reg_2, read_data_2);

        #5 clk = 1;
        #5 clk = 0;

        // test reset
        $display("\n-=-=-=- TEST REGISTER RESET -=-=-=-");
        reset = 1;

        #5 clk = 1;
        #5 clk = 0;

        assert(read_data_1 == 0);
        assert(read_data_2 == 0);
        $display("[READ EVENT]\tREG%d\t->%d",read_reg_1, read_data_1);
        $display("[READ EVENT]\tREG%d\t->%d",read_reg_2, read_data_2);


    end
endmodule

rtl/register/mips_register_file_tb.vcd
$date
	Thu Nov 25 09:20:26 2021
$end
$version
	Icarus Verilog
$end
$timescale
	100ps
$end
$scope module mips_register_file_tb $end
$var wire 32 ! read_data_v0 [31:0] $end
$var wire 32 " read_data_2 [31:0] $end
$var wire 32 # read_data_1 [31:0] $end
$var reg 1 $ clk $end
$var reg 5 % read_reg_1 [4:0] $end
$var reg 5 & read_reg_2 [4:0] $end
$var reg 1 ' reset $end
$var reg 32 ( write_data [31:0] $end
$var reg 1 ) write_enable $end
$var reg 5 * write_reg [4:0] $end
$scope module inst_reg $end
$var wire 1 $ clk $end
$var wire 32 + read_data_v0 [31:0] $end
$var wire 5 , read_reg_1 [4:0] $end
$var wire 5 - read_reg_2 [4:0] $end
$var wire 1 ' reset $end
$var wire 32 . write_data [31:0] $end
$var wire 1 ) write_enable $end
$var wire 5 / write_reg [4:0] $end
$var wire 32 0 read_data_2 [31:0] $end
$var wire 32 1 read_data_1 [31:0] $end
$scope begin $ivl_for_loop0 $end
$var integer 32 2 i [31:0] $end
$upscope $end
$upscope $end
$upscope $end
$enddefinitions $end
#0
$dumpvars
b0 2
bx 1
bx 0
b0 /
b0 .
bx -
bx ,
bx +
b0 *
0)
b0 (
1'
bx &
bx %
0$
bx #
bx "
bx !
$end
#50
b0 !
b0 +
b100000 2
1$
#100
b0 #
b0 1
b10000 %
b10000 ,
b10000 *
b10000 /
b100101101011010000111 (
b100101101011010000111 .
1)
0'
0$
#150
b100101101011010000111 #
b100101101011010000111 1
1$
#200
0)
0$
#250
1$
#300
b0 "
b0 0
b10100 &
b10100 -
b10100 *
b10100 /
b11101001100101110110001 (
b11101001100101110110001 .
1)
0$
#350
b11101001100101110110001 "
b11101001100101110110001 0
1$
#400
0)
0$
#450
1$
#500
1'
0$
#550
b0 "
b0 0
b0 #
b0 1
b100000 2
1$
